CHANGELOG.rst
LICENSE
MANIFEST.in
README.rst
requirements.txt
setup.py
acmin/__init__.py
acmin/apps.py
acmin/cache.py
acmin/forms.py
acmin/processors.py
acmin/signals.py
acmin/sql.py
acmin/management/__init__.py
acmin/management/commands/__init__.py
acmin/management/commands/createroot.py
acmin/management/commands/import.py
acmin/middlewares/__init__.py
acmin/middlewares/log.py
acmin/migrations/0001_initial.py
acmin/migrations/0002_auto_20190614_1843.py
acmin/migrations/0003_auto_20190614_1907.py
acmin/migrations/__init__.py
acmin/models/__init__.py
acmin/models/base.py
acmin/models/choice.py
acmin/models/config.py
acmin/models/contenttype.py
acmin/models/field.py
acmin/models/filter.py
acmin/models/group.py
acmin/models/permission.py
acmin/models/user.py
acmin/router/__init__.py
acmin/serializer/__init__.py
acmin/static/acmin/ace/css/ace-ie.min.css
acmin/static/acmin/ace/css/ace-part2.min.css
acmin/static/acmin/ace/css/ace-rtl.min.css
acmin/static/acmin/ace/css/ace-skins.min.css
acmin/static/acmin/ace/css/ace.min.css
acmin/static/acmin/ace/css/bootstrap-colorpicker.min.css
acmin/static/acmin/ace/css/bootstrap-datepicker3.min.css
acmin/static/acmin/ace/css/bootstrap-datetimepicker.min.css
acmin/static/acmin/ace/css/bootstrap-duallistbox.min.css
acmin/static/acmin/ace/css/bootstrap-editable.min.css
acmin/static/acmin/ace/css/bootstrap-multiselect.min.css
acmin/static/acmin/ace/css/bootstrap-timepicker.min.css
acmin/static/acmin/ace/css/bootstrap.min.css
acmin/static/acmin/ace/css/chosen.min.css
acmin/static/acmin/ace/css/colorbox.min.css
acmin/static/acmin/ace/css/daterangepicker.min.css
acmin/static/acmin/ace/css/dropzone.min.css
acmin/static/acmin/ace/css/font-awesome.min.css
acmin/static/acmin/ace/css/fonts.googleapis.com.css
acmin/static/acmin/ace/css/fullcalendar.min.css
acmin/static/acmin/ace/css/jquery-ui.custom.min.css
acmin/static/acmin/ace/css/jquery-ui.min.css
acmin/static/acmin/ace/css/jquery.gritter.min.css
acmin/static/acmin/ace/css/prettify.min.css
django_acmin.egg-info/PKG-INFO
django_acmin.egg-info/SOURCES.txt
django_acmin.egg-info/dependency_links.txt
django_acmin.egg-info/not-zip-safe
django_acmin.egg-info/requires.txt
django_acmin.egg-info/top_level.txt