Metadata-Version: 1.1
Name: django-acmin
Version: 1.0.0
Summary: Admin and API template for start a django web
Home-page: https://github.com/hikelee/django-acmin
Author: Hike Li
Author-email: hikelee@gmail.com
License: BSD
Platform: UNKNOWN
Classifier: Development Status :: 5 - Production/Stable
Classifier: Framework :: Django
Classifier: Intended Audience :: Developers
Classifier: License :: OSI Approved :: BSD License
Classifier: Operating System :: OS Independent
Classifier: Framework :: Django :: 2.1
Classifier: Programming Language :: Python :: 3.6
Classifier: Programming Language :: Python :: 3.7
Classifier: Topic :: Internet :: WWW/HTTP
